filter_and_pagination/__init__.py
filter_and_pagination-1.0.9.dist-info/LICENSE.txt
filter_and_pagination-1.0.9.dist-info/METADATA
filter_and_pagination-1.0.9.dist-info/WHEEL
filter_and_pagination-1.0.9.dist-info/top_level.txt
filter_and_pagination-1.0.9.dist-info/RECORD
