Metadata-Version: 2.1
Name: filter-and-pagination
Version: 1.0.9
Summary: Filter and Pagination in Django
Home-page: https://github.com/ashish1997it/
Author: Ashish Sondagar
Author-email: sondagarashish@gmail.com
License: UNKNOWN
Platform: UNKNOWN
Classifier: Programming Language :: Python :: 3
Classifier: License :: OSI Approved :: MIT License
Classifier: Operating System :: OS Independent
